{
	"__v" : NumberInt("0"),
	"_id" : ObjectId("591433e352d3f0140e6447b4"),
	"image" : "https://uphinhnhanh.com/images/2017/02/27/10kmua1.jpg",
	"link_href" : "http://10kmua.vn/san-pham/xe-tay-ga-honda-air-blade-tu-tinh-2017-xam-den-192.html",
	"name" : "Xe máy air blade",
	"sequence" : NumberInt("1"),
	"slug" : "xe-may-air-blade",
	"state" : NumberInt("1"),
	"type" : "slice"
},
{
	"__v" : NumberInt("0"),
	"_id" : ObjectId("5914341052d3f0140e6447b5"),
	"image" : "https://uphinhnhanh.com/images/2017/02/27/10kmua.jpg",
	"link_href" : "http://10kmua.vn/san-pham/iphone-7-plus-256gb-172.html",
	"name" : "Điện thoại",
	"sequence" : NumberInt("2"),
	"slug" : "dien-thoai",
	"state" : NumberInt("1"),
	"type" : "slice"
},
{
	"__v" : NumberInt("0"),
	"_id" : ObjectId("5914343052d3f0140e6447b6"),
	"image" : "https://uphinhnhanh.com/images/2017/03/01/10kmuadongho.jpg",
	"link_href" : "/danh-muc/sap-cong-bo/ong-ho-16.html",
	"name" : "Đồng hồ",
	"sequence" : NumberInt("3"),
	"slug" : "dong-ho",
	"state" : NumberInt("1"),
	"type" : "slice"
},
{
	"__v" : NumberInt("0"),
	"_id" : ObjectId("5914345552d3f0140e6447b7"),
	"image" : "https://uphinhnhanh.com/images/2017/03/01/10kmualaptop.jpg",
	"link_href" : "http://10kmua.vn/danh-muc/sap-cong-bo/laptop-37.html",
	"name" : "Laptop",
	"sequence" : NumberInt("4"),
	"slug" : "laptop",
	"state" : NumberInt("1"),
	"type" : "slice"
},
{
	"__v" : NumberInt("0"),
	"_id" : ObjectId("5914347d52d3f0140e6447b8"),
	"image" : "https://uphinhnhanh.com/images/2017/03/01/10kmuaphukien.jpg",
	"link_href" : "http://10kmua.vn/danh-muc/sap-cong-bo/phu-kien-38.html",
	"name" : "Phụ kiện",
	"sequence" : NumberInt("5"),
	"slug" : "phu-kien",
	"state" : NumberInt("1"),
	"type" : "slice"
},
{
	"__v" : NumberInt("0"),
	"_id" : ObjectId("591434bf52d3f0140e6447b9"),
	"image" : "/assets/images/themes/tim-hieu-ve-10k.png",
	"link_href" : "/tro-giup/huong-dan-choi.html",
	"name" : "Tìm hiểu về 10k",
	"sequence" : NumberInt("1"),
	"slug" : "tim-hieu-ve-10k",
	"state" : NumberInt("1"),
	"type" : "right"
},
{
	"__v" : NumberInt("0"),
	"_id" : ObjectId("591434e852d3f0140e6447ba"),
	"image" : "http://i.imgur.com/rMJCHIN.png",
	"link_href" : "/tro-giup/uy-tin.html",
	"name" : "Uy tín",
	"sequence" : NumberInt("1"),
	"slug" : "uy-tin",
	"state" : NumberInt("1"),
	"type" : "item"
},
{
	"__v" : NumberInt("0"),
	"_id" : ObjectId("5914351352d3f0140e6447bb"),
	"image" : "http://i.imgur.com/BiANR8L.png",
	"link_href" : "/tro-giup/dam-bao.html",
	"name" : "Đảm bảo",
	"sequence" : NumberInt("2"),
	"slug" : "dam-bao",
	"state" : NumberInt("1"),
	"type" : "item"
},
{
	"__v" : NumberInt("0"),
	"_id" : ObjectId("5914353252d3f0140e6447bc"),
	"image" : "http://i.imgur.com/4UCa6lL.png",
	"link_href" : "/tro-giup/cong-bang.html",
	"name" : "Công bằng",
	"sequence" : NumberInt("3"),
	"slug" : "cong-bang",
	"state" : NumberInt("1"),
	"type" : "item"
},
{
	"__v" : NumberInt("0"),
	"_id" : ObjectId("5914355852d3f0140e6447bd"),
	"image" : "http://i.imgur.com/HL6cNX3.png",
	"link_href" : "/tro-giup/chung-nhan-nha-nuoc.html",
	"name" : "Chứng nhận nhà nước",
	"sequence" : NumberInt("4"),
	"slug" : "chung-nhan-nha-nuoc",
	"state" : NumberInt("1"),
	"type" : "item"
},
{
	"__v" : NumberInt("0"),
	"_id" : ObjectId("5914357e52d3f0140e6447be"),
	"image" : "http://i.imgur.com/dhKCAPl.png",
	"link_href" : "/tro-giup/minh-bach.html",
	"name" : "Minh bạch",
	"sequence" : NumberInt("5"),
	"slug" : "minh-bach",
	"state" : NumberInt("1"),
	"type" : "item"
},
{
	"__v" : NumberInt("0"),
	"_id" : ObjectId("591435a4973133d17bf5d71e"),
	"image" : "http://i.imgur.com/EiwGZkc.png",
	"link_href" : "/tro-giup/them.html",
	"name" : "Thêm",
	"sequence" : NumberInt("6"),
	"slug" : "them",
	"state" : NumberInt("1"),
	"type" : "item"
},
{
	"__v" : NumberInt("0"),
	"_id" : ObjectId("591435cb973133d17bf5d71f"),
	"image" : "http://local1.icsc.vn:9971/assets/images/banner/banner-33.jpg",
	"link_href" : "http://local1.icsc.vn:9971/assets/images/banner/banner-33.jpg",
	"name" : "Sản phẩm hạn chế",
	"sequence" : NumberInt("1"),
	"slug" : "san-pham-han-che",
	"state" : NumberInt("1"),
	"type" : "limited"
},
{
	"__v" : NumberInt("0"),
	"_id" : ObjectId("591435ea973133d17bf5d720"),
	"image" : "https://lh3.googleusercontent.com/-4N9KRNg4lZQ/Voj5MRGJ2BI/AAAAAAAABY8/Zvv8zYUGr5A/w1535-h568-no/banner%2Bt%25E1%25BA%25BFt.png",
	"link_href" : "https://lh3.googleusercontent.com/-4N9KRNg4lZQ/Voj5MRGJ2BI/AAAAAAAABY8/Zvv8zYUGr5A/w1535-h568-no/banner%2Bt%25E1%25BA%25BFt.png",
	"name" : "123",
	"sequence" : NumberInt("2"),
	"slug" : "123",
	"state" : NumberInt("1"),
	"type" : "limited"
},
{
	"__v" : NumberInt("0"),
	"_id" : ObjectId("59143630973133d17bf5d721"),
	"image" : "https://lh3.googleusercontent.com/-4N9KRNg4lZQ/Voj5MRGJ2BI/AAAAAAAABY8/Zvv8zYUGr5A/w1535-h568-no/banner%2Bt%25E1%25BA%25BFt.png",
	"link_href" : "https://lh3.googleusercontent.com/-4N9KRNg4lZQ/Voj5MRGJ2BI/AAAAAAAABY8/Zvv8zYUGr5A/w1535-h568-no/banner%2Bt%25E1%25BA%25BFt.png",
	"name" : "dau xanh rau muong",
	"sequence" : NumberInt("3"),
	"slug" : "dau-xanh-rau-muong",
	"state" : NumberInt("1"),
	"type" : "limited"
},
